srchbooks.py
srchbooks-0.1.6.dist-info/entry_points.txt
srchbooks-0.1.6.dist-info/LICENSE
srchbooks-0.1.6.dist-info/METADATA
srchbooks-0.1.6.dist-info/WHEEL
srchbooks-0.1.6.dist-info/RECORD
